ml_adapter/sdk/__init__.py
ml_adapter/sdk/py.typed
ml_adapter/sdk/tool.py
waylay_ml_adapter_sdk-0.1.1.dist-info/licenses/LICENCE.txt
waylay_ml_adapter_sdk-0.1.1.dist-info/METADATA
waylay_ml_adapter_sdk-0.1.1.dist-info/WHEEL
waylay_ml_adapter_sdk-0.1.1.dist-info/entry_points.txt
waylay_ml_adapter_sdk-0.1.1.dist-info/top_level.txt
waylay_ml_adapter_sdk-0.1.1.dist-info/RECORD
