Metadata-Version: 2.4
Name: waylay-ml-adapter-sdk
Version: 0.1.1
Summary: ML_adapter plugin for waylay-sdk-py.
Author-email: Waylay <info@waylay.io>
Requires-Python: >=3.11
License-File: LICENCE.txt
Requires-Dist: waylay-ml-adapter-base
Requires-Dist: waylay-sdk-registry
Requires-Dist: waylay-sdk-rules
Requires-Dist: tenacity
Provides-Extra: dev
Requires-Dist: waylay-ml-adapter-base; extra == "dev"
Requires-Dist: urlpath; extra == "dev"
Requires-Dist: waylay-ml-adapter-devtools; extra == "dev"
Dynamic: license-file
